dicewars/__init__.py
dicewars/__version__.py
dicewars/game.py
dicewars/grid.py
dicewars/match.py
dicewars/player.py
dicewars/util.py
dicewars-0.2.0.dist-info/COPYING
dicewars-0.2.0.dist-info/METADATA
dicewars-0.2.0.dist-info/WHEEL
dicewars-0.2.0.dist-info/top_level.txt
dicewars-0.2.0.dist-info/RECORD
