Metadata-Version: 2.1
Name: dicewars
Version: 0.2.0
Summary: Backend for DiceWars games/servers
Home-page: https://github.com/scotty007/dicewars
Author: Thomas Schott
Author-email: scotty@c-base.org
License: UNKNOWN
Platform: UNKNOWN
Classifier: Topic :: Games/Entertainment :: Board Games
Classifier: Intended Audience :: Developers
Classifier: Operating System :: OS Independent
Classifier: Programming Language :: Python :: 3 :: Only
Classifier: Development Status :: 4 - Beta
Classifier: License :: OSI Approved :: GNU General Public License v3 or later (GPLv3+)
Requires-Python: >=3.7
